tables_io/__init__.py
tables_io/_version.py
tables_io/cli.py
tables_io/lazy_modules.py
tables_io/table_dict.py
tables_io/types.py
tables_io/conv/__init__.py
tables_io/conv/conv_table.py
tables_io/conv/conv_tabledict.py
tables_io/hdf5/__init__.py
tables_io/io_utils/__init__.py
tables_io/io_utils/iterator.py
tables_io/io_utils/read.py
tables_io/io_utils/write.py
tables_io/utils/__init__.py
tables_io/utils/array_utils.py
tables_io/utils/concat_utils.py
tables_io/utils/slice_utils.py
tables_io-1.0.1.dist-info/licenses/LICENSE
tables_io-1.0.1.dist-info/METADATA
tables_io-1.0.1.dist-info/WHEEL
tables_io-1.0.1.dist-info/entry_points.txt
tables_io-1.0.1.dist-info/top_level.txt
tables_io-1.0.1.dist-info/RECORD
