Metadata-Version: 2.4
Name: tables-io
Version: 1.0.1
Summary: Input/output and conversion functions for tabular data
Author-email: Eric Charles <echarles@slac.stanford.edu>
License: MIT License
Classifier: Development Status :: 4 - Beta
Classifier: License :: OSI Approved :: MIT License
Classifier: Intended Audience :: Developers
Classifier: Intended Audience :: Science/Research
Classifier: Operating System :: OS Independent
Classifier: Programming Language :: Python
Requires-Python: >=3.9
License-File: LICENSE
Requires-Dist: numpy>=1.21.0
Requires-Dist: click
Requires-Dist: deprecated>=1.2.0
Requires-Dist: tables>=3.0
Requires-Dist: h5py>=2.9
Requires-Dist: pandas>=2.0
Provides-Extra: full
Requires-Dist: astropy; extra == "full"
Requires-Dist: pyarrow; extra == "full"
Provides-Extra: dev
Requires-Dist: astropy; extra == "dev"
Requires-Dist: h5py>=2.9; extra == "dev"
Requires-Dist: pandas>=2.0; extra == "dev"
Requires-Dist: pyarrow; extra == "dev"
Requires-Dist: mpi4py; extra == "dev"
Requires-Dist: coverage; extra == "dev"
Requires-Dist: pylint; extra == "dev"
Requires-Dist: pytest; extra == "dev"
Requires-Dist: pytest-cov; extra == "dev"
Requires-Dist: flake8; extra == "dev"
Requires-Dist: jax>=0.4; extra == "dev"
Requires-Dist: jaxlib; extra == "dev"
Requires-Dist: pre-commit; extra == "dev"
Requires-Dist: sphinx>6.3.1; extra == "dev"
Requires-Dist: sphinx_rtd_theme; extra == "dev"
Requires-Dist: sphinx-autoapi; extra == "dev"
Requires-Dist: sphinx_design; extra == "dev"
Requires-Dist: myst-nb; extra == "dev"
Requires-Dist: sphinx-copybutton; extra == "dev"
Dynamic: license-file
